lab_1806_vec_db-0.8.1.dist-info/METADATA
lab_1806_vec_db-0.8.1.dist-info/WHEEL
lab_1806_vec_db-0.8.1.dist-info/licenses/LICENSE
lab_1806_vec_db/__init__.py
lab_1806_vec_db/__init__.pyi
lab_1806_vec_db/lab_1806_vec_db.cp311-win_amd64.pyd
lab_1806_vec_db/py.typed
lab_1806_vec_db-0.8.1.dist-info/RECORD
