Metadata-Version: 2.4
Name: lab-1806-vec-db
Version: 0.8.1
Classifier: Programming Language :: Rust
Classifier: Programming Language :: Python :: Implementation :: CPython
Classifier: Programming Language :: Python :: Implementation :: PyPy
License-File: LICENSE
Requires-Python: >=3.10, <3.13
